vreg/__init__.py
vreg/data.py
vreg/fake.py
vreg/metrics.py
vreg/mod_affine.py
vreg/mod_freeform.py
vreg/optimize.py
vreg/plot.py
vreg/rw.py
vreg/scipy_least_squares.py
vreg/utils.py
vreg/vol.py
vreg/datafiles/__init__.py
vreg-0.0.13.dist-info/licenses/LICENSE
vreg-0.0.13.dist-info/METADATA
vreg-0.0.13.dist-info/WHEEL
vreg-0.0.13.dist-info/top_level.txt
vreg-0.0.13.dist-info/RECORD
