Metadata-Version: 2.4
Name: vreg
Version: 0.0.13
Summary: 3D arrays with spatial awareness
Author-email: Steven Sourbron <s.sourbron@sheffield.ac.uk>
License:                                  Apache License
Project-URL: Homepage, https://openmiblab.github.io/vreg/
Project-URL: Source Code, https://github.com/openmiblab/vreg-package
Keywords: python,medical imaging,coregistration,MRI
Classifier: Development Status :: 3 - Alpha
Classifier: Intended Audience :: Developers
Classifier: Intended Audience :: Science/Research
Classifier: Topic :: Scientific/Engineering
Classifier: Operating System :: OS Independent
Classifier: License :: OSI Approved :: Apache Software License
Classifier: Programming Language :: Python
Classifier: Programming Language :: Python :: 3
Requires-Python: >=3.6
License-File: LICENSE
Requires-Dist: importlib-resources>=1.1.0
Requires-Dist: tqdm
Requires-Dist: numpy
Requires-Dist: scipy
Requires-Dist: scikit-image
Requires-Dist: requests
Requires-Dist: nibabel
Requires-Dist: zarr
Provides-Extra: plot
Requires-Dist: pyvista; extra == "plot"
Requires-Dist: matplotlib; extra == "plot"
Dynamic: license-file
